bypasssafe/__init__.py
bypasssafe/__main__.py
bypasssafe/account.py
bypasssafe/database.py
bypasssafe/main.py
bypasssafe/pass_gen.py
bypasssafe-1.32.dist-info/METADATA
bypasssafe-1.32.dist-info/WHEEL
bypasssafe-1.32.dist-info/RECORD
