Metadata-Version: 2.1
Name: bypasssafe
Version: 1.32
Summary: Valt de senhas e gerador
Author: MarcosDalessandro
Author-email: marcosdalessandroclima@ufpi.edu.br
Requires-Python: >=3.8,<4.0
Classifier: Programming Language :: Python :: 3
Classifier: Programming Language :: Python :: 3.8
Classifier: Programming Language :: Python :: 3.9
Classifier: Programming Language :: Python :: 3.10
Classifier: Programming Language :: Python :: 3.11
Classifier: Programming Language :: Python :: 3.12
Requires-Dist: bcrypt (>=3.2.0,<4.0.0)
Requires-Dist: psycopg2 (>=2.9.9,<3.0.0)
Requires-Dist: python-decouple (>=3.5,<4.0)
